{
  "$schema": "https://developer.microsoft.com/json-schemas/fabric/item/report/definition/visualContainer/2.7.0/schema.json",
  "name": "efadc238af2cc0d61bfd",
  "position": {
    "x": 1066.3979848866497,
    "y": 0,
    "z": 2000,
    "height": 63.476070528967249,
    "width": 214.00503778337529,
    "tabOrder": 2000
  },
  "visual": {
    "visualType": "image",
    "objects": {
      "image": [
        {
          "properties": {
            "sourceType": {
              "expr": {
                "Literal": {
                  "Value": "'imageData'"
                }
              }
            },
            "sourceField": {
              "expr": {
                "Measure": {
                  "Expression": {
                    "SourceRef": {
                      "Entity": "A_Measure"
                    }
                  },
                  "Property": "Notice"
                }
              }
            }
          }
        }
      ]
    },
    "drillFilterOtherVisuals": true
  }
}