{
  "$schema": "https://developer.microsoft.com/json-schemas/fabric/item/report/definition/page/2.1.0/schema.json",
  "name": "b27c2c0641847e447693",
  "displayName": "All in PPH Shipping Details",
  "displayOption": "FitToPage",
  "height": 720,
  "width": 1280,
  "filterConfig": {
    "filters": [
      {
        "name": "a482c6c138ae5237998a",
        "field": {
          "Measure": {
            "Expression": {
              "SourceRef": {
                "Entity": "A_Measure"
              }
            },
            "Property": "1_All in PPH Shipping"
          }
        },
        "type": "Categorical",
        "howCreated": "Drillthrough"
      },
      {
        "name": "7bfd02f0b157022bc753",
        "field": {
          "Measure": {
            "Expression": {
              "SourceRef": {
                "Entity": "A_Measure"
              }
            },
            "Property": "1_All in PPH Shipping Hours"
          }
        },
        "type": "Categorical",
        "howCreated": "Drillthrough"
      },
      {
        "name": "88fb0c00e00d00bacdb5",
        "field": {
          "Measure": {
            "Expression": {
              "SourceRef": {
                "Entity": "A_Measure"
              }
            },
            "Property": "1_All in PPH Shipping Pieces"
          }
        },
        "type": "Categorical",
        "howCreated": "Drillthrough"
      },
      {
        "name": "0a25985901ec8f80839c",
        "field": {
          "Column": {
            "Expression": {
              "SourceRef": {
                "Entity": "Dim_Team"
              }
            },
            "Property": "Team"
          }
        },
        "type": "Advanced",
        "howCreated": "User"
      }
    ]
  },
  "pageBinding": {
    "name": "cb97cbbb12e8476eccc7",
    "type": "Drillthrough",
    "parameters": [
      {
        "name": "2987e0852eb7e51a06a7",
        "boundFilter": "a482c6c138ae5237998a",
        "fieldExpr": {
          "Measure": {
            "Expression": {
              "SourceRef": {
                "Entity": "A_Measure"
              }
            },
            "Property": "1_All in PPH Shipping"
          }
        }
      },
      {
        "name": "f707619107e9556c63c8",
        "boundFilter": "7bfd02f0b157022bc753",
        "fieldExpr": {
          "Measure": {
            "Expression": {
              "SourceRef": {
                "Entity": "A_Measure"
              }
            },
            "Property": "1_All in PPH Shipping Hours"
          }
        }
      },
      {
        "name": "945280b06902d29a1655",
        "boundFilter": "88fb0c00e00d00bacdb5",
        "fieldExpr": {
          "Measure": {
            "Expression": {
              "SourceRef": {
                "Entity": "A_Measure"
              }
            },
            "Property": "1_All in PPH Shipping Pieces"
          }
        }
      }
    ]
  },
  "objects": {
    "outspacePane": [
      {
        "properties": {
          "backgroundColor": {
            "solid": {
              "color": {
                "expr": {
                  "ThemeDataColor": {
                    "ColorId": 4,
                    "Percent": 0
                  }
                }
              }
            }
          },
          "foregroundColor": {
            "solid": {
              "color": {
                "expr": {
                  "ThemeDataColor": {
                    "ColorId": 1,
                    "Percent": 0
                  }
                }
              }
            }
          }
        }
      }
    ]
  },
  "visibility": "HiddenInViewMode"
}